adder.v
// Adder circuit
`define NOT not #50
`define AND and #50
`define OR or #50
`define NAND nand #50
`define NOR nor #50
`define XOR xor #50

module behavioralFullAdder
(
    output sum, 
    output carryout,
    input a, 
    input b, 
    input carryin
);
    // Uses concatenation operator and built-in '+'
    assign {carryout, sum}=a+b+carryin;
endmodule

module structuralFullAdder
(
    output sum, 
    output carryout,
    input a, 
    input b, 
    input carryin
);
    // Your adder code here
    wire G, P, PandCin;

    `AND generator(G, a, b);
    `XOR propagate(P, a,b);

    `AND carry(PandCin, P, carryin);
    `OR Cout(carryout, PandCin, G);
    `XOR summation(sum, P, carryin);
endmodule

adder.t.v
// Adder testbench
`timescale 1 ns / 1 ps
`include "adder.v"

module testFullAdder();
    reg a, b, carryin;
    wire sum, carryout;

    // behavioralFullAdder adder (sum, carryout, a, b, carryin);
    structuralFullAdder adder (sum, carryout, a, b, carryin);

    initial begin
        a = 0; b = 0; carryin = 0; #100
        $dumpfile("adder.vcd");
        $dumpvars(0, adder);

        $display("Cin a  b | Cout  Sum | Expected Output");     // Header for the truth table for nAandnB
        a = 0; b = 0; carryin = 0; #1000
        $display(" %b  %b  %b |  %b     %b  |   0b00", carryin, a, b, carryout, sum);
        a = 0; b = 1; carryin = 0; #1000
        $display(" %b  %b  %b |  %b     %b  |   0b01", carryin, a, b, carryout, sum);
        a = 1; b = 0; carryin = 0; #1000
        $display(" %b  %b  %b |  %b     %b  |   0b01", carryin, a, b, carryout, sum);
        a = 1; b = 1; carryin = 0; #1000
        $display(" %b  %b  %b |  %b     %b  |   0b10", carryin, a, b, carryout, sum);
        a = 0; b = 0; carryin = 1; #1000
        $display(" %b  %b  %b |  %b     %b  |   0b01", carryin, a, b, carryout, sum);
        a = 0; b = 1; carryin = 1; #1000
        $display(" %b  %b  %b |  %b     %b  |   0b10", carryin, a, b, carryout, sum);
        a = 1; b = 0; carryin = 1; #1000
        $display(" %b  %b  %b |  %b     %b  |   0b10", carryin, a, b, carryout, sum);
        a = 1; b = 1; carryin = 1; #1000
        $display(" %b  %b  %b |  %b     %b  |   0b11", carryin, a, b, carryout, sum);
        
    end
endmodule

adder.vcd
$date
	Mon Sep 17 23:51:52 2018
$end
$version
	Icarus Verilog
$end
$timescale
	1ps
$end
$scope module testFullAdder $end
$scope module adder $end
$var wire 1 ! G $end
$var wire 1 " P $end
$var wire 1 # PandCin $end
$var wire 1 $ a $end
$var wire 1 % b $end
$var wire 1 & carryin $end
$var wire 1 ' carryout $end
$var wire 1 ( sum $end
$upscope $end
$upscope $end
$enddefinitions $end
#100000
$dumpvars
0(
0'
0&
0%
0$
0#
0"
0!
$end
#1100000
1%
#1150000
1"
#1200000
1(
#2100000
0%
1$
#3100000
1%
#3150000
1!
0"
#3200000
1'
0(
#4100000
1&
0%
0$
#4150000
1(
0!
#4200000
0'
#5100000
1%
#5150000
1"
#5200000
1#
0(
#5250000
1'
#6100000
0%
1$
#7100000
1%
#7150000
1!
0"
#7200000
0#
1(
