decoder.v
// Decoder circuit
`define NOT not #50
`define AND and #50
`define OR or #50
`define NAND nand #50
`define NOR nor #50
`define XOR xor #50

// module behavioralDecoder
// (
//     output out0, out1, out2, out3,
//     input address0, address1,
//     input enable
// );
//     // Uses concatenation and shift operators
//     assign {out3,out2,out1,out0}=enable<<{address1,address0};
// endmodule


module structuralDecoder
(
    output out0, out1, out2, out3,
    input address0, address1,
    input enable
);
    // Your decoder code here
    wire nA0, nA1;
    `NOT not0(nA0, address0);
    `NOT not1(nA1, address1);

    `AND and0(out0, nA0, nA1, enable);
    `AND and1(out1, address0, nA1, enable);
    `AND and2(out2, nA0, address1, enable);
    `AND and3(out3, address0, address1, enable);
endmodule

decoder.t.v
// Decoder testbench
`timescale 1 ns / 1 ps
`include "decoder.v"

module testDecoder (); 
    reg addr0, addr1;
    reg enable;
    wire out0,out1,out2,out3;

    // behavioralDecoder decoder (out0,out1,out2,out3,addr0,addr1,enable);
    structuralDecoder decoder (out0,out1,out2,out3,addr0,addr1,enable); // Swap after testing

    initial begin
        enable = 0; addr0 = 0; addr1 = 0; #100
        $dumpfile("decoder.vcd");
        $dumpvars(0, decoder);
    
        $display("En A0 A1| O0 O1 O2 O3 | Expected Output");
        enable=0;addr0=0;addr1=0; #1000 
        $display("%b  %b  %b |  %b  %b  %b  %b | All false", enable, addr0, addr1, out0, out1, out2, out3);
        enable=0;addr0=1;addr1=0; #1000
        $display("%b  %b  %b |  %b  %b  %b  %b | All false", enable, addr0, addr1, out0, out1, out2, out3);
        enable=0;addr0=0;addr1=1; #1000 
        $display("%b  %b  %b |  %b  %b  %b  %b | All false", enable, addr0, addr1, out0, out1, out2, out3);
        enable=0;addr0=1;addr1=1; #1000 
        $display("%b  %b  %b |  %b  %b  %b  %b | All false", enable, addr0, addr1, out0, out1, out2, out3);
        enable=1;addr0=0;addr1=0; #1000 
        $display("%b  %b  %b |  %b  %b  %b  %b | O0 Only", enable, addr0, addr1, out0, out1, out2, out3);
        enable=1;addr0=1;addr1=0; #1000 
        $display("%b  %b  %b |  %b  %b  %b  %b | O1 Only", enable, addr0, addr1, out0, out1, out2, out3);
        enable=1;addr0=0;addr1=1; #1000 
        $display("%b  %b  %b |  %b  %b  %b  %b | O2 Only", enable, addr0, addr1, out0, out1, out2, out3);
        enable=1;addr0=1;addr1=1; #1000 
        $display("%b  %b  %b |  %b  %b  %b  %b | O3 Only", enable, addr0, addr1, out0, out1, out2, out3);
    end

endmodule

decoder.vcd
$date
	Mon Sep 17 17:45:37 2018
$end
$version
	Icarus Verilog
$end
$timescale
	1ps
$end
$scope module testDecoder $end
$scope module decoder $end
$var wire 1 ! address0 $end
$var wire 1 " address1 $end
$var wire 1 # enable $end
$var wire 1 $ nA0 $end
$var wire 1 % nA1 $end
$var wire 1 & out0 $end
$var wire 1 ' out1 $end
$var wire 1 ( out2 $end
$var wire 1 ) out3 $end
$upscope $end
$upscope $end
$enddefinitions $end
#100000
$dumpvars
0)
0(
0'
0&
1%
1$
0#
0"
0!
$end
#1100000
1!
#1150000
0$
#2100000
1"
0!
#2150000
0%
1$
#3100000
1!
#3150000
0$
#4100000
0"
0!
1#
#4150000
1%
1$
#4200000
1&
#5100000
1!
#5150000
0$
1'
#5200000
0&
#6100000
1"
0!
#6150000
0%
1$
0'
#6200000
1(
#7100000
1!
#7150000
0$
1)
#7200000
0(
