multiplexer.v
// Multiplexer circuit
`define NOT not #50
`define AND and #50
`define OR or #50
`define NAND nand #50
`define NOR nor #50
`define XOR xor #50

// module behavioralMultiplexer
// (
//     output out,
//     input address0, address1,
//     input in0, in1, in2, in3
// );
//     // Join single-bit inputs into a bus, use address as index
//     wire[3:0] inputs = {in3, in2, in1, in0};
//     wire[1:0] address = {address1, address0};
//     assign out = inputs[address];
// endmodule


module structuralMultiplexer
(
    output out,
    input address0, address1,
    input in0, in1, in2, in3
);
    // Your multiplexer code here
    wire nA0, nA1;
    wire i0nA0nA1, i1A0nA1, i2nA0A1, i3A0A1;

    `NOT invA0(nA0, address0);
    `NOT invA1(nA1, address1);

    `AND and0(i0nA0nA1, in0, nA0, nA1);
    `AND and1(i1A0nA1, in1, address0, nA1);
    `AND and2(i2nA0A1, in2, nA0, address1);
    `AND and3(i3A0A1, in3, address0, address1);

    `OR orgate(out, i0nA0nA1, i1A0nA1, i2nA0A1, i3A0A1);
endmodule

multiplexer.t.v
// Multiplexer testbench
`timescale 1 ns / 1 ps
`include "multiplexer.v"

module testMultiplexer ();
    reg a0, a1, in0, in1, in2, in3;
    wire out;

    // behavioralMultiplexer mux(out, a0, a1, in0, in1, in2, in3);
    structuralMultiplexer mux(out, a0, a1, in0, in1, in2, in3);

    initial begin
      a0 = 0; a1 = 0; in0 = 0; in1 = 0; in2 = 0; in3 = 0; #100
      $dumpfile("mux.vcd");
      $dumpvars(0, mux);

      // initialize all to zero
      a0 = 0; a1 = 0; in0 = 0; in1 = 0; in2 = 0; in3 = 0; #1000
      $display("a0  a1  in0  in1  in2  in3  | out | Expected Output");
      // select in0
      a0 = 0; a1 = 0; in0 = 1; in1 = 0; in2 = 0; in3 = 0; #1000
      $display("%b    %b    %b    %b    %b    %b  |   %b | in0", a0, a1, in0, in1, in2, in3, out);
      a0 = 0; a1 = 0; in0 = 0; in1 = 1; in2 = 1; in3 = 1; #1000
      $display("%b    %b    %b    %b    %b    %b  |   %b | in0", a0, a1, in0, in1, in2, in3, out);
      // select in1
      a0 = 1; a1 = 0; in0 = 0; in1 = 1; in2 = 0; in3 = 0; #1000
      $display("%b    %b    %b    %b    %b    %b  |   %b | in1", a0, a1, in0, in1, in2, in3, out);
      a0 = 1; a1 = 0; in0 = 1; in1 = 0; in2 = 1; in3 = 1; #1000
      $display("%b    %b    %b    %b    %b    %b  |   %b | in1", a0, a1, in0, in1, in2, in3, out);
      // select in2
      a0 = 0; a1 = 1; in0 = 0; in1 = 0; in2 = 1; in3 = 0; #1000
      $display("%b    %b    %b    %b    %b    %b  |   %b | in2", a0, a1, in0, in1, in2, in3, out);
      a0 = 0; a1 = 1; in0 = 1; in1 = 1; in2 = 0; in3 = 1; #1000
      $display("%b    %b    %b    %b    %b    %b  |   %b | in2", a0, a1, in0, in1, in2, in3, out);
      // select in3
      a0 = 1; a1 = 1; in0 = 0; in1 = 0; in2 = 0; in3 = 1; #1000
      $display("%b    %b    %b    %b    %b    %b  |   %b | in3", a0, a1, in0, in1, in2, in3, out);
      a0 = 1; a1 = 1; in0 = 1; in1 = 1; in2 = 1; in3 = 0; #1000
      $display("%b    %b    %b    %b    %b    %b  |   %b | in3", a0, a1, in0, in1, in2, in3, out);
    end
endmodule

mux.vcd
$date
	Mon Sep 17 17:45:33 2018
$end
$version
	Icarus Verilog
$end
$timescale
	1ps
$end
$scope module testMultiplexer $end
$scope module mux $end
$var wire 1 ! address0 $end
$var wire 1 " address1 $end
$var wire 1 # i0nA0nA1 $end
$var wire 1 $ i1A0nA1 $end
$var wire 1 % i2nA0A1 $end
$var wire 1 & i3A0A1 $end
$var wire 1 ' in0 $end
$var wire 1 ( in1 $end
$var wire 1 ) in2 $end
$var wire 1 * in3 $end
$var wire 1 + nA0 $end
$var wire 1 , nA1 $end
$var wire 1 - out $end
$upscope $end
$upscope $end
$enddefinitions $end
#100000
$dumpvars
0-
1,
1+
0*
0)
0(
0'
0&
0%
0$
0#
0"
0!
$end
#1100000
1'
#1150000
1#
#1200000
1-
#2100000
1*
1)
1(
0'
#2150000
0#
#2200000
0-
#3100000
0*
0)
1!
#3150000
0+
1$
#3200000
1-
#4100000
1*
1)
0(
1'
#4150000
0$
#4200000
0-
#5100000
0*
0'
1"
0!
#5150000
0,
1+
#5200000
1%
#5250000
1-
#6100000
1*
0)
1(
1'
#6150000
0%
#6200000
0-
#7100000
0(
0'
1!
#7150000
0+
1&
#7200000
1-
#8100000
0*
1)
1(
1'
#8150000
0&
#8200000
0-
